micropub/__init__.py
micropub/admin.py
micropub/apps.py
micropub/forms.py
micropub/models.py
micropub/utils.py
micropub/views.py
micropub/migrations/0001_initial.py
micropub/migrations/__init__.py
django_micropub-0.0.1.dist-info/LICENSE
django_micropub-0.0.1.dist-info/METADATA
django_micropub-0.0.1.dist-info/WHEEL
django_micropub-0.0.1.dist-info/top_level.txt
django_micropub-0.0.1.dist-info/RECORD
